LICENSE
README.md
pyproject.toml
setup.cfg
setup.py
versioneer.py
apwarrant.egg-info/PKG-INFO
apwarrant.egg-info/SOURCES.txt
apwarrant.egg-info/dependency_links.txt
apwarrant.egg-info/requires.txt
apwarrant.egg-info/top_level.txt
apwarrant.egg-info/zip-safe
warrant/__init__.py
warrant/_version.py
warrant/aws_srp.py
warrant/exceptions.py
warrant/tests/__init__.py
warrant/tests/tests.py